LICENSE
MANIFEST.in
README.rst
requirements.txt
setup.cfg
setup.py
ckanext/__init__.py
ckanext/resourceauthorizer/__init__.py
ckanext/resourceauthorizer/commands.py
ckanext/resourceauthorizer/controller.py
ckanext/resourceauthorizer/helpers.py
ckanext/resourceauthorizer/model.py
ckanext/resourceauthorizer/plugin.py
ckanext/resourceauthorizer/logic/__init__.py
ckanext/resourceauthorizer/logic/action.py
ckanext/resourceauthorizer/logic/auth.py
ckanext/resourceauthorizer/logic/schema.py
ckanext/resourceauthorizer/logic/validators.py
ckanext/resourceauthorizer/templates/package/resource_edit_base.html
ckanext/resourceauthorizer/templates/resource-authorizer/acl.html
ckanext/resourceauthorizer/templates/resource-authorizer/acl_new.html
ckanext/resourceauthorizer/tests/__init__.py
ckanext/resourceauthorizer/tests/test_plugin.py
ckanext_resourceauthorizer.egg-info/PKG-INFO
ckanext_resourceauthorizer.egg-info/SOURCES.txt
ckanext_resourceauthorizer.egg-info/dependency_links.txt
ckanext_resourceauthorizer.egg-info/entry_points.txt
ckanext_resourceauthorizer.egg-info/namespace_packages.txt
ckanext_resourceauthorizer.egg-info/top_level.txt