Metadata-Version: 1.1
Name: ckanext-resourceauthorizer
Version: 0.0.1
Summary: An extension for authorizing resources
Home-page: https://github.com/etri-sodas/ckanext-resourceauthorizer
Author: Chau Nguyen
Author-email: chau@etri.re.kr
License: AGPL
Keywords: CKAN
Platform: UNKNOWN
Classifier: Development Status :: 4 - Beta
Classifier: License :: OSI Approved :: GNU Affero General Public License v3 or later (AGPLv3+)
Classifier: Programming Language :: Python :: 2.7
